<?xml version="1.0" encoding="utf-8" ?>
<objects xmlns="http://www.springframework.net"
         xmlns:r="http://www.springframework.net/remoting">
	
	<description>cao</description>

  <r:caoFactory id="AppDvBcService" remoteTargetName="AppDvBcService" 
                serviceUrl="tcp://localhost:8005" />
  <r:caoFactory id="AppGroupsService" remoteTargetName="AppGroupsService"
                 serviceUrl="tcp://localhost:8005" />
  <r:caoFactory id="DmDonviService" remoteTargetName="DmDonviService"
                 serviceUrl="tcp://localhost:8005" />
  <r:caoFactory id="AppUsersService" remoteTargetName="AppUsersService"
                 serviceUrl="tcp://localhost:8005" />
  
  <!--
		Old fashion way without remoting config parser...
	<object id="calculatorService" type="Spring.Remoting.CaoFactoryObject, Spring.Services">
		<property name="RemoteTargetName" value="prototypeCalculator" />
		<property name="ServiceUrl" value="tcp://localhost:8005" />
	</object>
  -->
	
</objects>